Metadata-Version: 2.1
Name: unskript-cloudnative-infra
Version: 1.0.1456
Summary: Opensource unSkript Python Package repository
Home-page: https://github.com/unskript/unskript.git
Author: unSkript Authors
Author-email: info@unskript.com
License: GNU General Public License v3
Keywords: unskript
Platform: UNKNOWN
Classifier: Development Status :: 2 - Pre-Alpha
Classifier: Intended Audience :: Developers
Classifier: License :: OSI Approved :: GNU General Public License v3 (GPLv3)
Classifier: Natural Language :: English
Classifier: Programming Language :: Python :: 3
Classifier: Programming Language :: Python :: 3.6
Classifier: Programming Language :: Python :: 3.7
Classifier: Programming Language :: Python :: 3.8
Requires-Python: >=3.6
License-File: LICENSE
License-File: AUTHORS.rst
Requires-Dist: azure-common (==1.1.28)
Requires-Dist: boto3 (==1.17.107)
Requires-Dist: botocore (==1.20.112)
Requires-Dist: google-api-core (>=1.31.2)
Requires-Dist: google-api-python-client (>=2.76.0)
Requires-Dist: google-cloud-bigquery-connection (>=1.7.3)
Requires-Dist: google-cloud-bigquery-datatransfer (>=3.7.3)
Requires-Dist: google-cloud-bigquery-logging (>=1.0.7)
Requires-Dist: google-cloud-bigquery-reservation (>=1.7.3)
Requires-Dist: google-cloud-bigquery-storage (>=2.16.2)
Requires-Dist: google-cloud-bigquery (>=3.3.6)
Requires-Dist: google-cloud-bigtable (>=2.13.2)
Requires-Dist: google-cloud-certificate-manager (>=1.1.1)
Requires-Dist: google-cloud-compute (>=1.6.1)
Requires-Dist: google-cloud-container (>=2.13.0)
Requires-Dist: google-cloud-filestore (>=1.2.3)
Requires-Dist: google-cloud-gke-hub (>=1.5.3)
Requires-Dist: google-cloud-iam (>=2.9.0)
Requires-Dist: google-cloud-kms (>=2.12.3)
Requires-Dist: google-cloud-logging (>=3.2.5)
Requires-Dist: google-cloud-memcache (>=1.4.4)
Requires-Dist: google-cloud-monitoring-dashboards (>=2.8.0)
Requires-Dist: google-cloud-monitoring (>=2.4.2)
Requires-Dist: google-cloud-network-connectivity (>=1.4.4)
Requires-Dist: google-cloud-secret-manager (>=2.5.0)
Requires-Dist: google-cloud-storage (>=2.5.0)
Requires-Dist: google-cloud-vpc-access (>=1.5.2)
Requires-Dist: kubernetes (==17.17.0)
Requires-Dist: matplotlib (==3.7.1)
Requires-Dist: msrestazure (==0.6.4)
Requires-Dist: tabulate (==0.8.9)
